viperthonix/__main__.py
viperthonix/basic.py
viperthonix/dataframe.py
viper_thonix-1.0.0.dist-info/LICENSE
viper_thonix-1.0.0.dist-info/METADATA
viper_thonix-1.0.0.dist-info/WHEEL
viper_thonix-1.0.0.dist-info/entry_points.txt
viper_thonix-1.0.0.dist-info/top_level.txt
viper_thonix-1.0.0.dist-info/RECORD
