Metadata-Version: 2.1
Name: viper-thonix
Version: 1.0.0
Summary: Tool to perform basic operations on your Dataset
Home-page: UNKNOWN
Author: Swati Pandey
License: MIT
Platform: UNKNOWN
Classifier: Programming Language :: Python :: 3
Classifier: Programming Language :: Python :: 3.6
Classifier: License :: OSI Approved :: MIT License
Classifier: Operating System :: OS Independent
Requires-Dist: pandas
Requires-Dist: pyinputplus
